torsh/__init__.py
torsh/cli.py
torsh/client.py
torsh/config.py
torsh/daemon.py
torsh/logging.py
torsh/ui/__init__.py
torsh/ui/app.py
torsh/ui/modals.py
torsh/ui/styles.tcss
torsh-0.1.2.dist-info/METADATA
torsh-0.1.2.dist-info/WHEEL
torsh-0.1.2.dist-info/entry_points.txt
torsh-0.1.2.dist-info/top_level.txt
torsh-0.1.2.dist-info/RECORD
