Metadata-Version: 2.4
Name: torsh
Version: 0.1.2
Summary: Transmission TUI client
Author: torsh authors
Requires-Python: >=3.10
Requires-Dist: textual>=0.60.0
Requires-Dist: transmission-rpc>=4.4.3
Requires-Dist: click>=8.1.7
Requires-Dist: pyyaml>=6.0.1
Requires-Dist: humanize>=4.9.0
